jvcprojector/__init__.py
jvcprojector/cli.py
jvcprojector/connection.py
jvcprojector/device.py
jvcprojector/error.py
jvcprojector/projector.py
jvcprojector/py.typed
jvcprojector/command/__init__.py
jvcprojector/command/base.py
jvcprojector/command/command.py
okasjvcprojector-2.0.1.dist-info/licenses/LICENSE
okasjvcprojector-2.0.1.dist-info/METADATA
okasjvcprojector-2.0.1.dist-info/WHEEL
okasjvcprojector-2.0.1.dist-info/entry_points.txt
okasjvcprojector-2.0.1.dist-info/top_level.txt
okasjvcprojector-2.0.1.dist-info/RECORD
