Metadata-Version: 2.4
Name: okasjvcprojector
Version: 2.0.1
Summary: A python client library for controlling a JVC Projector over a network connection.
Author-email: Nithin Juttuka <nithin.juttuka@miantic.com>
Project-URL: Homepage, https://github.com/Nithin-Miantic/okas-jvcprojector.git
Classifier: Development Status :: 5 - Production/Stable
Classifier: Intended Audience :: Developers
Classifier: License :: OSI Approved :: MIT License
Classifier: Topic :: Home Automation
Classifier: Topic :: Software Development :: Libraries
Classifier: Programming Language :: Python :: 3.10
Requires-Python: >=3.10
License-File: LICENSE
Provides-Extra: dev
Requires-Dist: build==1.3.0; extra == "dev"
Requires-Dist: coverage==7.13.0; extra == "dev"
Requires-Dist: mypy==1.19.0; extra == "dev"
Requires-Dist: pytest-asyncio==1.3.0; extra == "dev"
Requires-Dist: pytest==9.0.2; extra == "dev"
Requires-Dist: ruff==0.14.9; extra == "dev"
Requires-Dist: twine==6.2.0; extra == "dev"
Dynamic: license-file
